[
    {
        "id": 1,
        "name": "Portfolio Web",
        "img": "img/PortfolioSc.webp",
        "description": "A modern portfolio showcasing web and digital projects with details on creative solutions and skills. A reflection of dedication to digital excellence.",
        "techs": [
            1,
            7
        ],
        "urls": {
            "code": "https://github.com/Sandro96/Portfolio-Sandro-Ramirez"
        }
    },
    {
        "id": 2,
        "name": "Alkas Telecom",
        "img": "img/AlkasTelecomSc.webp",
        "description": "A landing page for Alkas Telecom, a fictional telecommunications company offering cutting-edge mobile plans and devices.",
        "techs": [
            1,3,
            4
        ],
        "urls": {
            "code": "https://github.com/Sandro96/alkastelecom",
            "view": "https://alkas-telecom.vercel.app",
            "design": "https://www.behance.net/gallery/138923963/Alkas-Telecom"
        }
    }
]
